azure_key_vault_report/__init__.py
azure_key_vault_report/az_cmd.py
azure_key_vault_report/azure_key_vault_report.py
azure_key_vault_report/azure_key_vault_report_bck.py
azure_key_vault_report/ste_report.py
azure_key_vault_report/lib/config.py
azure_key_vault_report/lib/html_table.py
azure_key_vault_report/lib/markdown.py
azure_key_vault_report/lib/ms_teams_json.py
azure_key_vault_report/lib/set_timestamp.py
ste_beta_rp-0.0.4.dist-info/METADATA
ste_beta_rp-0.0.4.dist-info/WHEEL
ste_beta_rp-0.0.4.dist-info/top_level.txt
ste_beta_rp-0.0.4.dist-info/RECORD
