Metadata-Version: 2.1
Name: ste-beta-rp
Version: 0.0.4
Summary: Output a Key Vault Secrets report
